nextgen/__init__.py
nextgen/connector/__init__.py
nextgen/connector/bingapi.py
nextgen_framework_alpha-0.0.1.dist-info/METADATA
nextgen_framework_alpha-0.0.1.dist-info/WHEEL
nextgen_framework_alpha-0.0.1.dist-info/top_level.txt
nextgen_framework_alpha-0.0.1.dist-info/RECORD
